KubiosDataLoader/KubiosLoader.py
KubiosDataLoader/__init__.py
KubiosDataLoader-0.1.1.dist-info/LICENSE
KubiosDataLoader-0.1.1.dist-info/METADATA
KubiosDataLoader-0.1.1.dist-info/WHEEL
KubiosDataLoader-0.1.1.dist-info/top_level.txt
KubiosDataLoader-0.1.1.dist-info/RECORD
