Metadata-Version: 2.1
Name: KubiosDataLoader
Version: 0.1.1
Summary: Importing text files from Kubios ECG data analysis
Home-page: https://github.com/MendyZaal/KubiosDataLoading
Author: Mendy Zaal
Author-email: mendyzaal@hotmail.com
License: gpl-3.0
Keywords: Kubios,dataloader,data-analysis
Platform: UNKNOWN
Classifier: Development Status :: 4 - Beta
Classifier: Intended Audience :: Science/Research
Classifier: Topic :: Software Development :: Build Tools
Classifier: License :: OSI Approved :: GNU General Public License v3 or later (GPLv3+)
Classifier: Programming Language :: Python :: 3
Classifier: Programming Language :: Python :: 3.4
Classifier: Programming Language :: Python :: 3.5
Classifier: Programming Language :: Python :: 3.6
Classifier: Programming Language :: Python :: 3.7
Requires-Dist: pandas
